blurwal/__init__.py
blurwal/__main__.py
blurwal/_version.py
blurwal/blur.py
blurwal/environment.py
blurwal/frame.py
blurwal/paths.py
blurwal/transition.py
blurwal/utils.py
blurwal/wallpaper.py
blurwal/windows.py
blurwal/x11.py
blurwal/backends/__init__.py
blurwal/backends/base.py
blurwal/backends/feh.py
blurwal/backends/xfconf.py
BlurWal-1.1.1.dist-info/LICENSE
BlurWal-1.1.1.dist-info/METADATA
BlurWal-1.1.1.dist-info/WHEEL
BlurWal-1.1.1.dist-info/entry_points.txt
BlurWal-1.1.1.dist-info/top_level.txt
BlurWal-1.1.1.dist-info/RECORD
