Metadata-Version: 2.1
Name: BlurWal
Version: 1.1.1
Summary: Smoothly blurs the wallpaper when windows are opened.
Home-page: https://gitlab.com/BVollmerhaus/blurwal
Author: Benedikt Vollmerhaus
Author-email: pypi@vollmerhaus.org
License: MIT
Download-URL: https://gitlab.com/BVollmerhaus/blurwal/-/archive/1.1.1/blurwal-1.1.1.tar.gz
Keywords: blur,wallpaper,desktop,ricing
Platform: UNKNOWN
Classifier: Development Status :: 5 - Production/Stable
Classifier: Environment :: X11 Applications
Classifier: License :: OSI Approved :: MIT License
Classifier: Operating System :: POSIX :: Linux
Classifier: Programming Language :: Python :: 3.6
Classifier: Topic :: Desktop Environment
Requires-Python: >=3.6
Requires-Dist: python-xlib
